jupyter_bbox_widget/__init__.py
jupyter_bbox_widget/bbox.py
jupyter_bbox_widget/static/main.mjs
jupyter_bbox_widget/static/style.css
jupyter_bbox_widget-0.6.0.dist-info/METADATA
jupyter_bbox_widget-0.6.0.dist-info/WHEEL
jupyter_bbox_widget-0.6.0.dist-info/licenses/LICENSE.txt
jupyter_bbox_widget-0.6.0.dist-info/RECORD
