Metadata-Version: 2.3
Name: jupyter_bbox_widget
Version: 0.6.0
Summary: A Jupyter widget for annotating images with bounding boxes
Project-URL: Homepage, https://github.com/gereleth/jupyter_bbox_widget
Author-email: gereleth <daria.voznyak@gmail.com>
License: Copyright (c) 2021 gereleth
License-File: LICENSE.txt
Keywords: Annotation,Image,Jupyter,Labeling,Widgets
Classifier: Framework :: Jupyter
Classifier: Intended Audience :: Developers
Classifier: Intended Audience :: Science/Research
Classifier: License :: OSI Approved :: BSD License
Classifier: Programming Language :: Python
Classifier: Programming Language :: Python :: 3
Requires-Python: >=3.7
Requires-Dist: anywidget>=0.9.0
Provides-Extra: dev
Requires-Dist: jupyterlab; extra == 'dev'
Requires-Dist: watchfiles; extra == 'dev'
